vinyldns/__init__.py
vinyldns/batch_change.py
vinyldns/boto_request_signer.py
vinyldns/client.py
vinyldns/membership.py
vinyldns/record.py
vinyldns/serdes.py
vinyldns/zone.py
vinyldns_python-0.9.8.dist-info/LICENSE
vinyldns_python-0.9.8.dist-info/LICENSE.asc
vinyldns_python-0.9.8.dist-info/METADATA
vinyldns_python-0.9.8.dist-info/NOTICE
vinyldns_python-0.9.8.dist-info/NOTICE.asc
vinyldns_python-0.9.8.dist-info/WHEEL
vinyldns_python-0.9.8.dist-info/top_level.txt
vinyldns_python-0.9.8.dist-info/RECORD
