Metadata-Version: 2.1
Name: vinyldns-python
Version: 0.9.8
Summary: Python client library for VinylDNS
Home-page: https://github.com/vinyldns/vinyldns-python
Author: vinyldns
Author-email: vinyldns-core@googlegroups.com
License: Apache Software License 2.0
Keywords: dns,python,vinyldns
Classifier: Development Status :: 5 - Production/Stable
Classifier: Intended Audience :: Developers
Classifier: Topic :: Internet :: Name Service (DNS)
Classifier: License :: OSI Approved :: Apache Software License
License-File: LICENSE
License-File: LICENSE.asc
License-File: NOTICE
License-File: NOTICE.asc
Requires-Dist: boto>=2.48.0
Requires-Dist: requests>=2.20.0
Requires-Dist: python-dateutil>=2.7.5
